django_dia/__init__.py
django_dia/diagram.py
django_dia/empty.xml
django_dia/models.py
django_dia/utils.py
django_dia/management/__init__.py
django_dia/management/commands/__init__.py
django_dia/management/commands/make_diagram.py
django_dia-0.4.9.dist-info/METADATA
django_dia-0.4.9.dist-info/WHEEL
django_dia-0.4.9.dist-info/top_level.txt
django_dia-0.4.9.dist-info/RECORD
