Metadata-Version: 2.1
Name: django-dia
Version: 0.4.9
Summary: Generate .dia diagram of your django project's models
Home-page: https://github.com/neumond/django_dia
Author: Vitalik Verhovodov
Author-email: knifeslaughter@gmail.com
License: MIT
Keywords: django dia model diagram
Platform: UNKNOWN
Classifier: Development Status :: 4 - Beta
Classifier: Intended Audience :: Developers
Classifier: License :: OSI Approved :: MIT License
Classifier: Programming Language :: Python :: 2
Classifier: Programming Language :: Python :: 3
Requires-Dist: Django
Requires-Dist: six
Provides-Extra: tests
Requires-Dist: pytest ; extra == 'tests'
Requires-Dist: pytest-django ; extra == 'tests'
Requires-Dist: pytest-pythonpath ; extra == 'tests'
